odoo/addons/account_move_line_date_order/LICENSE
odoo/addons/account_move_line_date_order/README.rst
odoo/addons/account_move_line_date_order/__init__.py
odoo/addons/account_move_line_date_order/__manifest__.py
odoo/addons/account_move_line_date_order/i18n/de.po
odoo/addons/account_move_line_date_order/i18n/de_CH.po
odoo/addons/account_move_line_date_order/images/screen.png
odoo/addons/account_move_line_date_order/models/__init__.py
odoo/addons/account_move_line_date_order/models/account_move_line.py
odoo/addons/account_move_line_date_order/static/description/icon.png
odoo/addons/account_move_line_date_order/static/description/index.html
odoo/addons/account_move_line_date_order/views/account_move_line_views.xml
odoo_addon_account_move_line_date_order-18.0.1.0.0.dist-info/METADATA
odoo_addon_account_move_line_date_order-18.0.1.0.0.dist-info/WHEEL
odoo_addon_account_move_line_date_order-18.0.1.0.0.dist-info/top_level.txt
odoo_addon_account_move_line_date_order-18.0.1.0.0.dist-info/RECORD
